README.txt
setup.cfg
setup.py
docs/HISTORY.txt
docs/INSTALL.txt
docs/LICENSE.GPL
docs/LICENSE.txt
italianskin/__init__.py
italianskin.tool.egg-info/PKG-INFO
italianskin.tool.egg-info/SOURCES.txt
italianskin.tool.egg-info/dependency_links.txt
italianskin.tool.egg-info/entry_points.txt
italianskin.tool.egg-info/namespace_packages.txt
italianskin.tool.egg-info/not-zip-safe
italianskin.tool.egg-info/paster_plugins.txt
italianskin.tool.egg-info/requires.txt
italianskin.tool.egg-info/top_level.txt
italianskin/tool/HISTORY.txt
italianskin/tool/README.txt
italianskin/tool/TODO.txt
italianskin/tool/__init__.py
italianskin/tool/config.py
italianskin/tool/configure.zcml
italianskin/tool/interfaces.py
italianskin/tool/profiles.zcml
italianskin/tool/skins.zcml
italianskin/tool/tests.py
italianskin/tool/version.txt
italianskin/tool/browser/__init__.py
italianskin/tool/browser/configure.zcml
italianskin/tool/browser/italianskintool.py
italianskin/tool/content/ItalianSkinTool.py
italianskin/tool/content/__init__.py
italianskin/tool/content/configure.zcml
italianskin/tool/profiles/default/actionicons.xml
italianskin/tool/profiles/default/controlpanel.xml
italianskin/tool/profiles/default/cssregistry.xml
italianskin/tool/profiles/default/factorytool.xml
italianskin/tool/profiles/default/skins.xml
italianskin/tool/profiles/default/toolset.xml
italianskin/tool/profiles/default/types.xml
italianskin/tool/profiles/default/types/ItalianSkinTool.xml
italianskin/tool/skins/is_tool_images/italianskin_tool.gif
italianskin/tool/skins/is_tool_styles/highcontrast.css.dtml
italianskin/tool/skins/is_tool_styles/highcontrast_padding.css.dtml
italianskin/tool/skins/is_tool_styles/italianskin.css.dtml
italianskin/tool/skins/is_tool_templates/accessibility-info.pt
italianskin/tool/skins/is_tool_templates/accessibility.js.dtml
italianskin/tool/skins/is_tool_templates/change_style.py
italianskin/tool/skins/is_tool_templates/main_template.pt
italianskin/tool/utils/__init__.py
italianskin/tool/utils/action_utils.py
