Metadata-Version: 1.0
Name: italianskin.tool
Version: 3.1.2-r1
Summary: italianskin tool
Home-page: http://www.redomino.com/it/labs/progetti/ItalianSkin
Author: Davide Moro (Redomino)
Author-email: davide.moro@redomino.com
License: GPL
Platform: UNKNOWN
Classifier: Framework :: Plone
Classifier: Framework :: Zope2
Classifier: Framework :: Zope3
Classifier: Programming Language :: Python
Classifier: Topic :: Software Development :: Libraries :: Python Modules
